{
  "sections": [
    {
      "id": "facial-skin",
      "title": "Facial & Skin Experts",
      "viewAllHref": "/experts",
      "experts": [
        {
          "id": "sophia-patel",
          "name": "Sophia Patel",
          "image": "https://images.unsplash.com/photo-1594744803329-e58b31de8bf5?auto=format&fit=crop&w=500&q=70",
          "verified": true,
          "specialty": "Skin Specialist",
          "rating": 4.9,
          "reviews": 128,
          "distance": "2.1 km away",
          "tags": ["Hydra Facial", "Acne Treatment"],
          "price": 90,
          "currency": "$",
          "gender": "female",
          "categoryId": "facial-skin"
        },
        {
          "id": "isabella-chen",
          "name": "Isabella Chen",
          "image": "https://images.unsplash.com/photo-1573497019940-1c28c88b4f3e?auto=format&fit=crop&w=500&q=70",
          "verified": true,
          "specialty": "Dermal Therapist",
          "rating": 4.8,
          "reviews": 96,
          "distance": "2.4 km away",
          "tags": ["Chemical Peel", "Microdermabrasion"],
          "price": 85,
          "currency": "$",
          "gender": "female",
          "categoryId": "facial-skin"
        },
        {
          "id": "emily-thompson",
          "name": "Emily Thompson",
          "image": "https://images.unsplash.com/photo-1614436163996-25cee5f54290?auto=format&fit=crop&w=500&q=70",
          "verified": true,
          "specialty": "Facial & Skin Expert",
          "rating": 4.7,
          "reviews": 86,
          "distance": "3.0 km away",
          "tags": ["Deep Cleansing", "LED Therapy"],
          "price": 75,
          "currency": "$",
          "gender": "female",
          "categoryId": "facial-skin"
        },
        {
          "id": "ava-martinez",
          "name": "Ava Martinez",
          "image": "https://images.unsplash.com/photo-1487412720507-e7ab37603c6f?auto=format&fit=crop&w=500&q=70",
          "verified": true,
          "specialty": "Skin Care Specialist",
          "rating": 4.9,
          "reviews": 112,
          "distance": "1.8 km away",
          "tags": ["Hydra Facial", "Dermaplaning"],
          "price": 95,
          "currency": "$",
          "gender": "female",
          "categoryId": "facial-skin"
        },
        {
          "id": "chloe-anderson",
          "name": "Chloe Anderson",
          "image": "https://images.unsplash.com/photo-1438761681033-6461ffad8d80?auto=format&fit=crop&w=500&q=70",
          "verified": true,
          "specialty": "Skin Therapist",
          "rating": 4.6,
          "reviews": 78,
          "distance": "2.6 km away",
          "tags": ["Anti-Aging", "Skin Rejuvenation"],
          "price": 80,
          "currency": "$",
          "gender": "female",
          "categoryId": "facial-skin"
        },
        {
          "id": "olivia-harris",
          "name": "Olivia Harris",
          "image": "https://images.unsplash.com/photo-1544005313-94ddf0286df2?auto=format&fit=crop&w=500&q=70",
          "verified": true,
          "specialty": "Cosmetic Skin Expert",
          "rating": 4.8,
          "reviews": 93,
          "distance": "3.2 km away",
          "tags": ["Brightening Facial", "Skin Consultation"],
          "price": 70,
          "currency": "$",
          "gender": "female",
          "categoryId": "facial-skin"
        }
      ]
    },
    {
      "id": "barbers",
      "title": "Barbers",
      "viewAllHref": "/experts",
      "experts": [
        {
          "id": "james-oliver",
          "name": "James Oliver",
          "image": "https://images.unsplash.com/photo-1507003211169-0a1dd7228f2d?auto=format&fit=crop&w=500&q=70",
          "verified": true,
          "specialty": "Barber",
          "rating": 4.9,
          "reviews": 230,
          "distance": "3.3 km away",
          "tags": ["Haircut", "Beard Trim", "Fade Cut"],
          "price": 40,
          "currency": "$",
          "gender": "male",
          "categoryId": "barbers"
        },
        {
          "id": "daniel-smith",
          "name": "Daniel Smith",
          "image": "https://images.unsplash.com/photo-1500648767791-00dcc994a43e?auto=format&fit=crop&w=500&q=70",
          "verified": true,
          "specialty": "Men's Hair Specialist",
          "rating": 4.8,
          "reviews": 152,
          "distance": "1.6 km away",
          "tags": ["Hair Styling", "Shave", "Beard Trim"],
          "price": 45,
          "currency": "$",
          "gender": "male",
          "categoryId": "barbers"
        },
        {
          "id": "michael-lee",
          "name": "Michael Lee",
          "image": "https://images.unsplash.com/photo-1506794778202-cad84cf45f1d?auto=format&fit=crop&w=500&q=70",
          "verified": true,
          "specialty": "Fade Expert",
          "rating": 4.7,
          "reviews": 98,
          "distance": "2.0 km away",
          "tags": ["Fade Cut", "Haircut", "Beard Trim"],
          "price": 50,
          "currency": "$",
          "gender": "male",
          "categoryId": "barbers"
        },
        {
          "id": "william-king",
          "name": "William King",
          "image": "https://images.unsplash.com/photo-1492562080023-ab3db95bfbce?auto=format&fit=crop&w=500&q=70",
          "verified": true,
          "specialty": "Senior Barber",
          "rating": 4.6,
          "reviews": 74,
          "distance": "3.1 km away",
          "tags": ["Classic Cut", "Shave", "Beard Trim"],
          "price": 45,
          "currency": "$",
          "gender": "male",
          "categoryId": "barbers"
        },
        {
          "id": "alexander-scott",
          "name": "Alexander Scott",
          "image": "https://images.unsplash.com/photo-1488161628813-04466f872be2?auto=format&fit=crop&w=500&q=70",
          "verified": true,
          "specialty": "Modern Barber",
          "rating": 4.7,
          "reviews": 112,
          "distance": "2.7 km away",
          "tags": ["Haircut", "Beard Trim", "Hair Styling"],
          "price": 50,
          "currency": "$",
          "gender": "male",
          "categoryId": "barbers"
        },
        {
          "id": "ethan-carter-barber",
          "name": "Ethan Carter",
          "image": "https://images.unsplash.com/photo-1599566150163-29194dcaad36?auto=format&fit=crop&w=500&q=70",
          "verified": true,
          "specialty": "Men's Grooming Expert",
          "rating": 4.8,
          "reviews": 86,
          "distance": "2.4 km away",
          "tags": ["Beard Grooming", "Shave", "Haircut"],
          "price": 45,
          "currency": "$",
          "gender": "male",
          "categoryId": "barbers"
        }
      ]
    },
    {
      "id": "massage-therapy",
      "title": "Massage Therapy",
      "viewAllHref": "/experts",
      "experts": [
        {
          "id": "liam-brown",
          "name": "Liam Brown",
          "image": "https://images.unsplash.com/photo-1472099645785-5658abf4ff4e?auto=format&fit=crop&w=500&q=70",
          "verified": true,
          "specialty": "Relaxation Therapist",
          "rating": 4.9,
          "reviews": 210,
          "distance": "2.2 km away",
          "tags": ["Deep Tissue", "Swedish", "Relaxation"],
          "price": 90,
          "currency": "$",
          "gender": "male",
          "categoryId": "massage-therapy"
        },
        {
          "id": "noah-wilson",
          "name": "Noah Wilson",
          "image": "https://images.unsplash.com/photo-1568602471122-7832951cc4c5?auto=format&fit=crop&w=500&q=70",
          "verified": true,
          "specialty": "Sports Massage Therapist",
          "rating": 4.8,
          "reviews": 130,
          "distance": "2.8 km away",
          "tags": ["Sports Massage", "Recovery", "Pain Relief"],
          "price": 100,
          "currency": "$",
          "gender": "male",
          "categoryId": "massage-therapy"
        },
        {
          "id": "ethan-carter-massage",
          "name": "Ethan Carter",
          "image": "https://images.unsplash.com/photo-1605462863863-10d9e47e15ee?auto=format&fit=crop&w=500&q=70",
          "verified": true,
          "specialty": "Remedial Massage Therapist",
          "rating": 4.7,
          "reviews": 89,
          "distance": "1.9 km away",
          "tags": ["Remedial", "Therapeutic", "Back Pain"],
          "price": 85,
          "currency": "$",
          "gender": "male",
          "categoryId": "massage-therapy"
        },
        {
          "id": "lucas-white",
          "name": "Lucas White",
          "image": "https://images.unsplash.com/photo-1500648767791-00dcc994a43e?auto=format&fit=crop&w=500&q=70",
          "verified": true,
          "specialty": "Holistic Massage Therapist",
          "rating": 4.6,
          "reviews": 67,
          "distance": "2.6 km away",
          "tags": ["Aromatherapy", "Relaxation", "Stress Relief"],
          "price": 80,
          "currency": "$",
          "gender": "male",
          "categoryId": "massage-therapy"
        },
        {
          "id": "henry-thomas",
          "name": "Henry Thomas",
          "image": "https://images.unsplash.com/photo-1519085360753-af0119f7cbe7?auto=format&fit=crop&w=500&q=70",
          "verified": true,
          "specialty": "Deep Tissue Specialist",
          "rating": 4.8,
          "reviews": 91,
          "distance": "2.3 km away",
          "tags": ["Deep Tissue", "Trigger Point"],
          "price": 95,
          "currency": "$",
          "gender": "male",
          "categoryId": "massage-therapy"
        },
        {
          "id": "mason-taylor",
          "name": "Mason Taylor",
          "image": "https://images.unsplash.com/photo-1463453091185-61582044d556?auto=format&fit=crop&w=500&q=70",
          "verified": true,
          "specialty": "Aromatherapy Therapist",
          "rating": 4.7,
          "reviews": 81,
          "distance": "3.0 km away",
          "tags": ["Aromatherapy", "Hot Stone"],
          "price": 85,
          "currency": "$",
          "gender": "male",
          "categoryId": "massage-therapy"
        }
      ]
    }
  ]
}
